MANIFEST.in
README.md
setup.py
PyEtf.egg-info/PKG-INFO
PyEtf.egg-info/SOURCES.txt
PyEtf.egg-info/dependency_links.txt
PyEtf.egg-info/requires.txt
PyEtf.egg-info/top_level.txt
pyetf/__init__.py
pyetf/functions.py
pyetf/finance/__init__.py
pyetf/finance/etf.py
pyetf/finance/portfolio.py
pyetf/frames/__init__.py
pyetf/frames/app.py
pyetf/frames/main_page/__init__.py
pyetf/frames/main_page/add_etf.py
pyetf/frames/main_page/etf_list.py
pyetf/frames/main_page/left_frame.py
pyetf/frames/main_page/main_page.py
pyetf/frames/main_page/right_frame.py
pyetf/frames/main_page/sell_etf.py
pyetf/frames/menu/__init__.py
pyetf/frames/menu/menu_bar.py
pyetf/frames/vs_index/__init__.py
pyetf/frames/vs_index/vs_index_page.py
pyetf/server/__init__.py
pyetf/server/client.py
scripts/GUI.py
scripts/Update.py