Metadata-Version: 1.1
Name: PyEtf
Version: 0.8.4
Summary: Manages yout Portfolio
Home-page: UNKNOWN
Author: Alfredo Mauri
Author-email: alfredo.mauri.2000@gmail.com
License: BSD
Keywords: python etfs portfoliomanager
Platform: all
Classifier: Intended Audience :: Education
Classifier: Operating System :: OS Independent
Classifier: Programming Language :: Python :: 3.7
Classifier: Topic :: Documentation
Classifier: Topic :: Education :: Testing
